{
  "nn_name":"sgmlTest",
  "decription":"sgml test program",
  "data":{
    "path": "../../data/mnist.pkl.gz",
    "type": "mnist_loader"
  },
  "parameters":{
    "solver":"SGD",
    "mini_batch_size": 100,
    "eta": 3,
    "epochs": 30,
    "costType" : "CrossEntropy"
  },
  "trace":{
    "trace_training_cost": 1,
    "trace_test_cost": 1,
    "trace_training_accuracy": 1,
    "trace_test_accuracy": 1
  },
  "layers":[
    {
      "layer_name":"input",
      "type":"InputLayer",
      "top":"hidden"
    },
    {
      "layer_name":"hidden1",
      "type":"FCLayer",
      "bottom":"input",
      "top":"output",
      "num_output":30
    },
    {
      "layer_name":"output",
      "type":"OutputLayer",
      "bottom":"hidden",
      "num_output":10,
      "top":""
    }
  ]
}